rby_uipath/OAuth2.py
rby_uipath/QueueDefinitions.py
rby_uipath/QueueItems.py
rby_uipath/__init__.py
rby_uipath-0.0.1.dist-info/LICENSE
rby_uipath-0.0.1.dist-info/METADATA
rby_uipath-0.0.1.dist-info/WHEEL
rby_uipath-0.0.1.dist-info/top_level.txt
rby_uipath-0.0.1.dist-info/RECORD
