Metadata-Version: 2.1
Name: rby-uipath
Version: 0.0.1
Summary: UiPath related tools.
Author-email: fstr11011 <michaelgladstein27@gmail.com>
License: Copyright (c) 2018 The Python Packaging Authority        
Project-URL: Homepage, https://github.com/fstr11011/UiPath_Api
Project-URL: Bug Tracker, https://github.com/fstr11011/UiPath_Api/issues
Classifier: Programming Language :: Python :: 3
Classifier: License :: OSI Approved :: MIT License
Classifier: Operating System :: OS Independent
Requires-Python: >=3.9
License-File: LICENSE
Requires-Dist: requests
